dci_umb/__init__.py
dci_umb/bus.py
dci_umb/cli.py
dci_umb/handler.py
dci_umb/main.py
dci_umb/receiver.py
dci_umb/sender.py
dci_umb/version.py
dci_umb-0.4.2.post202510211220.dist-info/LICENSE
dci_umb-0.4.2.post202510211220.dist-info/METADATA
dci_umb-0.4.2.post202510211220.dist-info/WHEEL
dci_umb-0.4.2.post202510211220.dist-info/entry_points.txt
dci_umb-0.4.2.post202510211220.dist-info/top_level.txt
dci_umb-0.4.2.post202510211220.dist-info/RECORD
