Metadata-Version: 2.1
Name: dci-umb
Version: 0.4.2.post202510211220
Summary: DCI umb module
Home-page: https://github.com/redhat-cip/dci-umb
Author: Distributed CI team
Author-email: distributed-ci@redhat.com
License: Apache v2.0
Classifier: License :: OSI Approved :: Apache Software License
Classifier: Operating System :: POSIX :: Linux
Classifier: Programming Language :: Python :: 2
Classifier: Programming Language :: Python :: 3
License-File: LICENSE
Requires-Dist: requests
Requires-Dist: python-qpid-proton
